cellstar/__init__.py
cellstar/segmentation.py
cellstar/core/__init__.py
cellstar/core/config.py
cellstar/core/image_repo.py
cellstar/core/point.py
cellstar/core/polar_transform.py
cellstar/core/seed.py
cellstar/core/seeder.py
cellstar/core/snake.py
cellstar/core/snake_filter.py
cellstar/core/parallel/__init__.py
cellstar/core/parallel/snake_grow.py
cellstar/parameter_fitting/__init__.py
cellstar/parameter_fitting/pf_auto_params.py
cellstar/parameter_fitting/pf_mutator.py
cellstar/parameter_fitting/pf_process.py
cellstar/parameter_fitting/pf_rank_process.py
cellstar/parameter_fitting/pf_rank_snake.py
cellstar/parameter_fitting/pf_runner.py
cellstar/parameter_fitting/pf_snake.py
cellstar/utils/__init__.py
cellstar/utils/calc_util.py
cellstar/utils/debug_util.py
cellstar/utils/image_util.py
cellstar/utils/index.py
cellstar/utils/params_util.py
CellStar-2.0.3.dist-info/METADATA
CellStar-2.0.3.dist-info/WHEEL
CellStar-2.0.3.dist-info/top_level.txt
CellStar-2.0.3.dist-info/RECORD
