Metadata-Version: 2.1
Name: CellStar
Version: 2.0.3
Summary: Algorithm for round cells identification in the brightfield microscopy images.
Home-page: https://github.com/Fafa87/cellstar
Author: Filip Mroz
Author-email: fafafft@gmail.com
License: BSD
Keywords: brightfield,yeast,segmentation,adapting
Platform: UNKNOWN
Classifier: Development Status :: 5 - Production/Stable
Classifier: Intended Audience :: Science/Research
Classifier: Operating System :: OS Independent
Classifier: Programming Language :: Python :: 2
Classifier: Programming Language :: Python :: 2.7
Classifier: Programming Language :: Python :: 3
Classifier: Programming Language :: Python :: 3.8
Classifier: Programming Language :: Python :: 3.9
Classifier: Topic :: Scientific/Engineering :: Bio-Informatics
Classifier: Topic :: Scientific/Engineering :: Image Recognition
Classifier: Topic :: Scientific/Engineering
Requires-Dist: numpy (>=1.16)
Requires-Dist: scipy (>=1.2.3)
Requires-Dist: pillow (<=6.2.2)
Requires-Dist: matplotlib (<=2.2.5)
Requires-Dist: imageio (<=2.6.1)
Requires-Dist: pathlib
